simplejrpc_gfile/__init__.py
simplejrpc_gfile/simplejrpc_gfile.py
simplejrpc_gfile/test/test_file.py
simplejrpc_gfile/test/zack.json
simplejrpc_gfile-0.0.3.dist-info/LICENSE.txt
simplejrpc_gfile-0.0.3.dist-info/METADATA
simplejrpc_gfile-0.0.3.dist-info/WHEEL
simplejrpc_gfile-0.0.3.dist-info/RECORD
