Metadata-Version: 2.3
Name: simplejrpc_gfile
Version: 0.0.3
Summary: GM file operator
License: MIT
Author: yao
Author-email: 1125564921@qq.com
Requires-Python: >=3.10,<4.0
Classifier: License :: OSI Approved :: MIT License
Classifier: Programming Language :: Python :: 3
Classifier: Programming Language :: Python :: 3.10
Classifier: Programming Language :: Python :: 3.11
Classifier: Programming Language :: Python :: 3.12
Classifier: Programming Language :: Python :: 3.13
